mlx/__main__.py
mlx/_os_warning.py
mlx/_reprlib_fix.py
mlx/distributed_run.py
mlx/extension.py
mlx/py.typed
mlx/utils.py
mlx/lib/libmlx.dylib
mlx/lib/mlx.metallib
mlx/nn/__init__.py
mlx/nn/init.py
mlx/nn/losses.py
mlx/nn/utils.py
mlx/optimizers/__init__.py
mlx/optimizers/optimizers.py
mlx/optimizers/schedulers.py
mlx_awni_test_2-0.0.2.dist-info/licenses/LICENSE
mlx_awni_test_2-0.0.2.dist-info/METADATA
mlx_awni_test_2-0.0.2.dist-info/WHEEL
mlx_awni_test_2-0.0.2.dist-info/entry_points.txt
mlx_awni_test_2-0.0.2.dist-info/top_level.txt
mlx_awni_test_2-0.0.2.dist-info/RECORD
