Metadata-Version: 2.4
Name: mlx-awni-test-2
Version: 0.0.2
Summary: A framework for machine learning on Apple silicon.
Home-page: https://github.com/ml-explore/mlx
Author: MLX Contributors
Author-email: mlx@group.apple.com
License: MIT
Requires-Python: >=3.9
License-File: LICENSE
Provides-Extra: dev
Requires-Dist: nanobind==2.4.0; extra == "dev"
Requires-Dist: numpy; extra == "dev"
Requires-Dist: pre-commit; extra == "dev"
Requires-Dist: setuptools>=42; extra == "dev"
Requires-Dist: torch; extra == "dev"
Requires-Dist: typing_extensions; extra == "dev"
Provides-Extra: cpu
Requires-Dist: mlx-awni-cpu==0.0.2; extra == "cpu"
Provides-Extra: cuda
Requires-Dist: mlx-cuda==0.0.2; extra == "cuda"
Dynamic: author
Dynamic: author-email
Dynamic: description
Dynamic: description-content-type
Dynamic: home-page
Dynamic: license
Dynamic: license-file
Dynamic: provides-extra
Dynamic: requires-python
Dynamic: summary
